setup.py
hellokitty/__init__.py
hellokitty/meow.py
hellokitty.egg-info/PKG-INFO
hellokitty.egg-info/SOURCES.txt
hellokitty.egg-info/dependency_links.txt
hellokitty.egg-info/top_level.txt