Metadata-Version: 1.0
Name: hellokitty
Version: 0.0.6
Summary: Some funny app!
Home-page: https://github.com/mindey/hellokitty
Author: Mindey
Author-email: mindey@qq.com
License: UNKNOWN
Platform: UNKNOWN
